CHANGES.rst
CONTRIBUTORS.rst
DEVELOP.rst
LICENSE.GPL
LICENSE.rst
MANIFEST.in
README.rst
constraints.txt
constraints_plone52.txt
requirements.txt
setup.cfg
setup.py
docs/conf.py
docs/index.rst
src/redturtle/__init__.py
src/redturtle.importer.volto.egg-info/PKG-INFO
src/redturtle.importer.volto.egg-info/SOURCES.txt
src/redturtle.importer.volto.egg-info/dependency_links.txt
src/redturtle.importer.volto.egg-info/entry_points.txt
src/redturtle.importer.volto.egg-info/namespace_packages.txt
src/redturtle.importer.volto.egg-info/not-zip-safe
src/redturtle.importer.volto.egg-info/requires.txt
src/redturtle.importer.volto.egg-info/top_level.txt
src/redturtle/importer/__init__.py
src/redturtle/importer/volto/__init__.py
src/redturtle/importer/volto/configure.zcml
src/redturtle/importer/volto/testing.py
src/redturtle/importer/volto/adapters/__init__.py
src/redturtle/importer/volto/adapters/configure.zcml
src/redturtle/importer/volto/adapters/volto_blocks.py
src/redturtle/importer/volto/tests/__init__.py
src/redturtle/importer/volto/tests/test_content_text_converter.py
src/redturtle/importer/volto/tests/test_draftjs_converter.py
src/redturtle/importer/volto/tests/test_migration.py
src/redturtle/importer/volto/transmogrifier/__init__.py
src/redturtle/importer/volto/transmogrifier/configure.zcml
src/redturtle/importer/volto/transmogrifier/fix_volto_references.py
src/redturtle/importer/volto/transmogrifier/types_mapping.py