Metadata-Version: 2.1
Name: redturtle.importer.volto
Version: 1.0.0
Summary: Importer from an old Plone Site into a new one with Volto
Home-page: https://github.com/collective/redturtle.importer.volto
Author: RedTurtle Technology
Author-email: sviluppoplone@redturtle.it
License: GPL version 2
Project-URL: PyPI, https://pypi.python.org/pypi/redturtle.importer.volto
Project-URL: Source, https://github.com/collective/redturtle.importer.volto
Project-URL: Tracker, https://github.com/collective/redturtle.importer.volto/issues
Keywords: Python Plone
Platform: UNKNOWN
Classifier: Environment :: Web Environment
Classifier: Framework :: Plone
Classifier: Framework :: Plone :: Addon
Classifier: Framework :: Plone :: 5.2
Classifier: Programming Language :: Python
Classifier: Programming Language :: Python :: 3.6
Classifier: Programming Language :: Python :: 3.7
Classifier: Operating System :: OS Independent
Classifier: License :: OSI Approved :: GNU General Public License v2 (GPLv2)
Requires-Python: >=3.6
Provides-Extra: test
